oface/__init__.py
oface/face_analysis.py
oface/core/__init__.py
oface/core/face_align.py
oface/model/__init__.py
oface/model/base.py
oface/model/face_detection.py
oface/model/face_recognition.py
oface-0.1.12.dist-info/LICENSE
oface-0.1.12.dist-info/METADATA
oface-0.1.12.dist-info/WHEEL
oface-0.1.12.dist-info/top_level.txt
oface-0.1.12.dist-info/RECORD
