Metadata-Version: 2.1
Name: oface
Version: 0.1.12
Summary: OFace.
Home-page: https://github.com/007gzs/oface
Author: 007
Author-email: 007gzs@gmail.com
License: MIT
Platform: UNKNOWN
Classifier: Programming Language :: Python
Classifier: Programming Language :: Python :: 3
Classifier: Programming Language :: Python :: 3 :: Only
Classifier: Programming Language :: Python :: 3.6
Classifier: Programming Language :: Python :: 3.7
Classifier: Programming Language :: Python :: 3.8
Classifier: Programming Language :: Python :: 3.9
Requires-Python: >=3.6
Requires-Dist: opencv-python
Requires-Dist: scikit-image
Requires-Dist: onnx
